dvc/.DS_Store
dvc/__init__.py
dvc/__main__.py
dvc/_debug.py
dvc/analytics.py
dvc/annotations.py
dvc/build.py
dvc/cachemgr.py
dvc/compare.py
dvc/config.py
dvc/config_schema.py
dvc/daemon.py
dvc/dagascii.py
dvc/data_cloud.py
dvc/database.py
dvc/dirs.py
dvc/dvcfile.py
dvc/env.py
dvc/exceptions.py
dvc/ignore.py
dvc/info.py
dvc/lock.py
dvc/log.py
dvc/logger.py
dvc/output.py
dvc/pathspec_math.py
dvc/progress.py
dvc/prompt.py
dvc/rwlock.py
dvc/schema.py
dvc/scm.py
dvc/types.py
dvc/updater.py
dvc/version.py
dvc/__pyinstaller/__init__.py
dvc/__pyinstaller/hook-asyncssh.py
dvc/__pyinstaller/hook-celery.py
dvc/__pyinstaller/hook-dvc.py
dvc/__pyinstaller/hook-dvc.utils.flatten.py
dvc/__pyinstaller/hook-dvc_task.py
dvc/__pyinstaller/hook-fsspec.py
dvc/__pyinstaller/hook-pydrive2.py
dvc/api/__init__.py
dvc/api/artifacts.py
dvc/api/data.py
dvc/api/dataset.py
dvc/api/experiments.py
dvc/api/scm.py
dvc/api/show.py
dvc/cli/__init__.py
dvc/cli/command.py
dvc/cli/completion.py
dvc/cli/formatter.py
dvc/cli/parser.py
dvc/cli/utils.py
dvc/commands/.DS_Store
dvc/commands/__init__.py
dvc/commands/add.py
dvc/commands/artifacts.py
dvc/commands/cache.py
dvc/commands/check_ignore.py
dvc/commands/checkout.py
dvc/commands/commit.py
dvc/commands/completion.py
dvc/commands/config.py
dvc/commands/daemon.py
dvc/commands/dag.py
dvc/commands/data.py
dvc/commands/data_sync.py
dvc/commands/dataset.py
dvc/commands/dataset_list.py
dvc/commands/destroy.py
dvc/commands/diff.py
dvc/commands/du.py
dvc/commands/exp_list.py
dvc/commands/freeze.py
dvc/commands/gc.py
dvc/commands/get.py
dvc/commands/get_url.py
dvc/commands/git_hook.py
dvc/commands/imp.py
dvc/commands/imp_db.py
dvc/commands/imp_url.py
dvc/commands/init.py
dvc/commands/install.py
dvc/commands/logs.py
dvc/commands/ls_url.py
dvc/commands/metrics.py
dvc/commands/metrics_diff.py
dvc/commands/move.py
dvc/commands/params.py
dvc/commands/plots.py
dvc/commands/remote.py
dvc/commands/remove.py
dvc/commands/repro.py
dvc/commands/root.py
dvc/commands/stage.py
dvc_mlplus-0.1.2.dist-info/licenses/LICENSE
dvc_mlplus-0.1.2.dist-info/METADATA
dvc_mlplus-0.1.2.dist-info/WHEEL
dvc_mlplus-0.1.2.dist-info/entry_points.txt
dvc_mlplus-0.1.2.dist-info/top_level.txt
dvc_mlplus-0.1.2.dist-info/RECORD
