Metadata-Version: 2.4
Name: dvc-mlplus
Version: 0.1.2
Summary: Enhanced DVC with advanced MLOps commands and features.
Author-email: blueeye-040 <chandrumurugesan6@gmail.com>
License:                                  Apache License
Project-URL: Homepage, https://github.com/blueeye-040/dvc-enhanced-lib
Project-URL: Repository, https://github.com/blueeye-040/dvc-enhanced-lib
Requires-Python: >=3.7
License-File: LICENSE
Requires-Dist: aiohappyeyeballs==2.6.1
Requires-Dist: aiohttp==3.12.15
Requires-Dist: aiohttp-retry==2.9.1
Requires-Dist: aiosignal==1.4.0
Requires-Dist: amqp==5.3.1
Requires-Dist: annotated-types==0.7.0
Requires-Dist: antlr4-python3-runtime==4.9.3
Requires-Dist: appdirs==1.4.4
Requires-Dist: async-timeout==5.0.1
Requires-Dist: asyncssh==2.21.0
Requires-Dist: atpublic==6.0.1
Requires-Dist: attrs==25.3.0
Requires-Dist: billiard==4.2.1
Requires-Dist: celery==5.5.3
Requires-Dist: certifi==2025.8.3
Requires-Dist: cffi==2.0.0
Requires-Dist: charset-normalizer==3.4.3
Requires-Dist: click==8.1.8
Requires-Dist: click-didyoumean==0.3.1
Requires-Dist: click-plugins==1.1.1.2
Requires-Dist: click-repl==0.3.0
Requires-Dist: colorama==0.4.6
Requires-Dist: configobj==5.0.9
Requires-Dist: cryptography==45.0.7
Requires-Dist: dictdiffer==0.9.0
Requires-Dist: diskcache==5.6.3
Requires-Dist: distro==1.9.0
Requires-Dist: dpath==2.2.0
Requires-Dist: dulwich==0.24.1
Requires-Dist: dvc-data==3.16.12
Requires-Dist: dvc-http==2.32.0
Requires-Dist: dvc-objects==5.1.1
Requires-Dist: dvc-render==1.0.2
Requires-Dist: dvc-studio-client==0.22.0
Requires-Dist: dvc-task==0.40.2
Requires-Dist: entrypoints==0.4
Requires-Dist: filelock==3.19.1
Requires-Dist: flatten-dict==0.4.2
Requires-Dist: flufl.lock==8.2.0
Requires-Dist: frozenlist==1.7.0
Requires-Dist: fsspec==2025.9.0
Requires-Dist: funcy==2.0
Requires-Dist: gitdb==4.0.12
Requires-Dist: GitPython==3.1.45
Requires-Dist: grandalf==0.8
Requires-Dist: gto==1.8.0
Requires-Dist: hydra-core==1.3.2
Requires-Dist: idna==3.10
Requires-Dist: iterative-telemetry==0.0.10
Requires-Dist: kombu==5.5.4
Requires-Dist: markdown-it-py==3.0.0
Requires-Dist: mdurl==0.1.2
Requires-Dist: multidict==6.6.4
Requires-Dist: networkx==3.2.1
Requires-Dist: omegaconf==2.3.0
Requires-Dist: orjson==3.11.3
Requires-Dist: packaging==25.0
Requires-Dist: pathspec==0.12.1
Requires-Dist: platformdirs==4.4.0
Requires-Dist: prompt_toolkit==3.0.52
Requires-Dist: propcache==0.3.2
Requires-Dist: psutil==7.0.0
Requires-Dist: pycparser==2.23
Requires-Dist: pydantic==2.11.9
Requires-Dist: pydantic_core==2.33.2
Requires-Dist: pydot==4.0.1
Requires-Dist: pygit2==1.15.1
Requires-Dist: Pygments==2.19.2
Requires-Dist: pygtrie==2.5.0
Requires-Dist: pyparsing==3.2.4
Requires-Dist: python-dateutil==2.9.0.post0
Requires-Dist: PyYAML==6.0.2
Requires-Dist: requests==2.32.5
Requires-Dist: rich==14.1.0
Requires-Dist: ruamel.yaml==0.18.15
Requires-Dist: ruamel.yaml.clib==0.2.12
Requires-Dist: scmrepo==3.5.2
Requires-Dist: semver==3.0.4
Requires-Dist: shellingham==1.5.4
Requires-Dist: shortuuid==1.0.13
Requires-Dist: shtab==1.7.2
Requires-Dist: six==1.17.0
Requires-Dist: smmap==5.0.2
Requires-Dist: sqltrie==0.11.2
Requires-Dist: tabulate==0.9.0
Requires-Dist: tomlkit==0.13.3
Requires-Dist: tqdm==4.67.1
Requires-Dist: typer==0.17.4
Requires-Dist: typing-inspection==0.4.1
Requires-Dist: typing_extensions==4.15.0
Requires-Dist: tzdata==2025.2
Requires-Dist: urllib3==2.5.0
Requires-Dist: vine==5.1.0
Requires-Dist: voluptuous==0.15.2
Requires-Dist: wcwidth==0.2.13
Requires-Dist: yarl==1.20.1
Requires-Dist: zc.lockfile==3.0.post1
Dynamic: license-file
